README.md
setup.py
examples/__init__.py
examples/forms.py
examples/views.py
flask_wtf_storage/__init__.py
flask_wtf_storage/fields.py
flask_wtf_storage/forms.py
flask_wtf_storage/utils.py
flask_wtf_storage/widgets.py
flask_wtf_storage.egg-info/PKG-INFO
flask_wtf_storage.egg-info/SOURCES.txt
flask_wtf_storage.egg-info/dependency_links.txt
flask_wtf_storage.egg-info/requires.txt
flask_wtf_storage.egg-info/top_level.txt