Metadata-Version: 1.0
Name: flask-wtf-storage
Version: 0.0.2
Summary: extend flask-wtf to use google storage
Home-page: UNKNOWN
Author: liupeng
Author-email: liupeng.dalian@gmail.com
License: MIT License
Keywords: flask,wtf,storage,google storage
Platform: any
